subdown
