Metadata-Version: 1.0
Name: subdown
Version: 0.2.1
Summary: Reddit image scraper
Home-page: https://github.com/radiosilence/subdown
Author: James Cleveland
Author-email: jc@blackflags.co.uk
License: LICENSE.txt
Platform: UNKNOWN
